{
    "events": [
      {"EventID": 1, "Title": "Tech Conference", "Date": "2025-05-12", "Time": "09:00", "EventType": "Conference", "Location": "New York"},
      {"EventID": 2, "Title": "Music Festival", "Date": "2025-06-15", "Time": "18:00", "EventType": "Festival", "Location": "Los Angeles"},
      {"EventID": 3, "Title": "Art Exhibition", "Date": "2025-07-20", "Time": "11:00", "EventType": "Exhibition", "Location": "Paris"},
      {"EventID": 4, "Title": "Tech Conference", "Date": "2025-08-05", "Time": "10:00", "EventType": "Conference", "Location": "Berlin"},
      {"EventID": 5, "Title": "Yoga Retreat", "Date": "2025-09-18", "Time": "07:00", "EventType": "Retreat", "Location": "Bali"},
      {"EventID": 6, "Title": "Startup Workshop", "Date": "2025-10-02", "Time": "14:00", "EventType": "Workshop", "Location": "London"},
      {"EventID": 7, "Title": "Food Expo", "Date": "2025-11-10", "Time": "16:00", "EventType": "Expo", "Location": "Tokyo"},
      {"EventID": 8, "Title": "Fashion Show", "Date": "2025-12-01", "Time": "19:00", "EventType": "Show", "Location": "Milan"},
      {"EventID": 9, "Title": "Dance Night", "Date": "2026-01-15", "Time": "20:00", "EventType": "Night", "Location": "Dubai"},
      {"EventID": 10, "Title": "Tech Meetup", "Date": "2026-02-05", "Time": "17:00", "EventType": "Meetup", "Location": "San Francisco"},
      {"EventID": 11, "Title": "Tech Conference", "Date": "2025-07-20", "Time": "09:00", "EventType": "Conference", "Location": "New York"},
      {"EventID": 12, "Title": "Music Festival", "Date": "2025-10-15", "Time": "18:00", "EventType": "Festival", "Location": "Tokyo"},
      {"EventID": 13, "Title": "Art Exhibition", "Date": "2025-09-10", "Time": "11:00", "EventType": "Exhibition", "Location": "Paris"},
      {"EventID": 14, "Title": "Food Expo", "Date": "2025-06-30", "Time": "16:00", "EventType": "Expo", "Location": "Tokyo"},
      {"EventID": 15, "Title": "Yoga Retreat", "Date": "2025-12-18", "Time": "07:00", "EventType": "Retreat", "Location": "Bali"},
      {"EventID": 16, "Title": "Tech Meetup", "Date": "2025-11-05", "Time": "17:00", "EventType": "Meetup", "Location": "San Francisco"},
      {"EventID": 17, "Title": "Science Fair", "Date": "2025-08-20", "Time": "10:00", "EventType": "Fair", "Location": "Berlin"},
      {"EventID": 18, "Title": "Tech Conference", "Date": "2025-12-01", "Time": "09:00", "EventType": "Conference", "Location": "Los Angeles"},
      {"EventID": 19, "Title": "Music Festival", "Date": "2025-10-25", "Time": "18:00", "EventType": "Festival", "Location": "Milan"},
      {"EventID": 20, "Title": "Fashion Show", "Date": "2025-11-01", "Time": "19:00", "EventType": "Show", "Location": "Paris"},
      {"EventID": 21, "Title": "Yoga Retreat", "Date": "2025-05-01", "Time": "07:00", "EventType": "Retreat", "Location": "Bali"},
      {"EventID": 22, "Title": "Dance Night", "Date": "2025-12-20", "Time": "20:00", "EventType": "Night", "Location": "Dubai"},
      {"EventID": 23, "Title": "Science Fair", "Date": "2026-01-10", "Time": "10:00", "EventType": "Fair", "Location": "Berlin"},
      {"EventID": 24, "Title": "Food Expo", "Date": "2026-02-05", "Time": "16:00", "EventType": "Expo", "Location": "San Francisco"},
      {"EventID": 25, "Title": "Art Exhibition", "Date": "2025-08-15", "Time": "11:00", "EventType": "Exhibition", "Location": "New York"},
      {"EventID": 26, "Title": "Music Festival", "Date": "2025-07-22", "Time": "18:00", "EventType": "Festival", "Location": "Tokyo"},
      {"EventID": 27, "Title": "Tech Conference", "Date": "2025-06-10", "Time": "09:00", "EventType": "Conference", "Location": "San Francisco"},
      {"EventID": 28, "Title": "Fashion Show", "Date": "2025-11-15", "Time": "19:00", "EventType": "Show", "Location": "Milan"},
      {"EventID": 29, "Title": "Tech Meetup", "Date": "2026-01-30", "Time": "17:00", "EventType": "Meetup", "Location": "London"},
      {"EventID": 30, "Title": "Yoga Retreat", "Date": "2025-09-25", "Time": "07:00", "EventType": "Retreat", "Location": "Bali"},
      {"EventID": 31, "Title": "Dance Night", "Date": "2026-01-25", "Time": "20:00", "EventType": "Night", "Location": "Dubai"},
      {"EventID": 32, "Title": "Tech Meetup", "Date": "2025-12-01", "Time": "17:00", "EventType": "Meetup", "Location": "Los Angeles"},
      {"EventID": 33, "Title": "Food Expo", "Date": "2025-11-25", "Time": "16:00", "EventType": "Expo", "Location": "New York"},
      {"EventID": 34, "Title": "Yoga Retreat", "Date": "2026-02-10", "Time": "07:00", "EventType": "Retreat", "Location": "Bali"},
      {"EventID": 35, "Title": "Science Fair", "Date": "2025-07-25", "Time": "10:00", "EventType": "Fair", "Location": "Berlin"},
      {"EventID": 36, "Title": "Art Exhibition", "Date": "2026-01-30", "Time": "11:00", "EventType": "Exhibition", "Location": "Paris"},
      {"EventID": 37, "Title": "Music Festival", "Date": "2026-02-15", "Time": "18:00", "EventType": "Festival", "Location": "Los Angeles"},
      {"EventID": 38, "Title": "Food Expo", "Date": "2025-05-01", "Time": "16:00", "EventType": "Expo", "Location": "San Francisco"},
      {"EventID": 39, "Title": "Fashion Show", "Date": "2025-12-05", "Time": "19:00", "EventType": "Show", "Location": "Milan"},
      {"EventID": 40, "Title": "Yoga Retreat", "Date": "2025-06-10", "Time": "07:00", "EventType": "Retreat", "Location": "Bali"},
      {"EventID": 41, "Title": "Dance Night", "Date": "2025-11-01", "Time": "20:00", "EventType": "Night", "Location": "Dubai"},
      {"EventID": 42, "Title": "Tech Conference", "Date": "2026-02-01", "Time": "09:00", "EventType": "Conference", "Location": "Los Angeles"},
      {"EventID": 43, "Title": "Art Exhibition", "Date": "2025-09-15", "Time": "11:00", "EventType": "Exhibition", "Location": "New York"},
      {"EventID": 44, "Title": "Music Festival", "Date": "2025-07-01", "Time": "18:00", "EventType": "Festival", "Location": "Tokyo"},
      {"EventID": 45, "Title": "Fashion Show", "Date": "2025-10-25", "Time": "19:00", "EventType": "Show", "Location": "Paris"},
      {"EventID": 46, "Title": "Food Expo", "Date": "2025-12-20", "Time": "16:00", "EventType": "Expo", "Location": "San Francisco"},
      {"EventID": 47, "Title": "Dance Night", "Date": "2025-08-15", "Time": "20:00", "EventType": "Night", "Location": "Dubai"},
      {"EventID": 48, "Title": "Tech Meetup", "Date": "2025-09-30", "Time": "17:00", "EventType": "Meetup", "Location": "London"},
      {"EventID": 49, "Title": "Yoga Retreat", "Date": "2025-06-15", "Time": "07:00", "EventType": "Retreat", "Location": "Bali"},
      {"EventID": 50, "Title": "Science Fair", "Date": "2025-10-10", "Time": "10:00", "EventType": "Fair", "Location": "Berlin"}
    ]
  }
  